odoo8_addon_account_partner_required-8.0.0.1.0.99.dev13-py2.7-nspkg.pth
odoo8_addon_account_partner_required-8.0.0.1.0.99.dev13.dist-info/DESCRIPTION.rst
odoo8_addon_account_partner_required-8.0.0.1.0.99.dev13.dist-info/METADATA
odoo8_addon_account_partner_required-8.0.0.1.0.99.dev13.dist-info/RECORD
odoo8_addon_account_partner_required-8.0.0.1.0.99.dev13.dist-info/WHEEL
odoo8_addon_account_partner_required-8.0.0.1.0.99.dev13.dist-info/metadata.json
odoo8_addon_account_partner_required-8.0.0.1.0.99.dev13.dist-info/namespace_packages.txt
odoo8_addon_account_partner_required-8.0.0.1.0.99.dev13.dist-info/top_level.txt
odoo_addons/account_partner_required/__init__.py
odoo_addons/account_partner_required/__openerp__.py
odoo_addons/account_partner_required/account.py
odoo_addons/account_partner_required/account_view.xml
odoo_addons/account_partner_required/i18n/account_partner_required.pot
odoo_addons/account_partner_required/i18n/ar.po
odoo_addons/account_partner_required/i18n/bs.po
odoo_addons/account_partner_required/i18n/ca.po
odoo_addons/account_partner_required/i18n/cs.po
odoo_addons/account_partner_required/i18n/de.po
odoo_addons/account_partner_required/i18n/en_GB.po
odoo_addons/account_partner_required/i18n/es.po
odoo_addons/account_partner_required/i18n/es_CR.po
odoo_addons/account_partner_required/i18n/es_EC.po
odoo_addons/account_partner_required/i18n/es_MX.po
odoo_addons/account_partner_required/i18n/fr.po
odoo_addons/account_partner_required/i18n/hr.po
odoo_addons/account_partner_required/i18n/hu.po
odoo_addons/account_partner_required/i18n/id.po
odoo_addons/account_partner_required/i18n/it.po
odoo_addons/account_partner_required/i18n/ja.po
odoo_addons/account_partner_required/i18n/lt.po
odoo_addons/account_partner_required/i18n/mk.po
odoo_addons/account_partner_required/i18n/mn.po
odoo_addons/account_partner_required/i18n/nb.po
odoo_addons/account_partner_required/i18n/nl.po
odoo_addons/account_partner_required/i18n/nl_BE.po
odoo_addons/account_partner_required/i18n/nl_NL.po
odoo_addons/account_partner_required/i18n/pt.po
odoo_addons/account_partner_required/i18n/pt_BR.po
odoo_addons/account_partner_required/i18n/pt_PT.po
odoo_addons/account_partner_required/i18n/ro.po
odoo_addons/account_partner_required/i18n/ro_RO.po
odoo_addons/account_partner_required/i18n/ru.po
odoo_addons/account_partner_required/i18n/sl.po
odoo_addons/account_partner_required/i18n/sv.po
odoo_addons/account_partner_required/i18n/tr.po
odoo_addons/account_partner_required/i18n/zh_CN.po
